autisto/daemons.py
autisto/database.py
autisto/finances.py
autisto/server.py
autisto/spreadsheet.py
autisto/utils.py
autisto-1.1.1.dist-info/LICENSE
autisto-1.1.1.dist-info/METADATA
autisto-1.1.1.dist-info/WHEEL
autisto-1.1.1.dist-info/entry_points.txt
autisto-1.1.1.dist-info/top_level.txt
autisto-1.1.1.dist-info/RECORD
