Metadata-Version: 2.1
Name: autisto
Version: 1.1.1
Summary: Basic accounting (?) program integrated with Google Sheets to fulfill my own autistic needs of tracking the shit owned.
Author: Jan Grzybek
Author-email: lyre_embassy_0n@icloud.com
License: MIT
Project-URL: GitHub, https://github.com/jan-grzybek/autisto
Classifier: Development Status :: 5 - Production/Stable
Classifier: Intended Audience :: End Users/Desktop
Classifier: License :: OSI Approved :: MIT License
Classifier: Natural Language :: English
Classifier: Operating System :: MacOS :: MacOS X
Classifier: Operating System :: POSIX :: Linux
Classifier: Operating System :: Unix
Classifier: Programming Language :: Python :: 3 :: Only
Requires-Python: >=3.10
License-File: LICENSE
Requires-Dist: pymongo
Requires-Dist: gspread >=6.0.0
Requires-Dist: python-dateutil
